<?xml version="1.0" encoding="utf-8" ?>
<odoo>
    <data noupdate="1">
        <record id="freight_crm_lead_creation_notification_template" model="mail.template">
            <field name="name">CRM: Lead Creation Notification Template - Qweb</field>
            <field name="model_id" ref="crm.model_crm_lead" />
            <field name="subject">A new Lead has just been created in the system</field>
            <field name="email_from">noreply@viet-toan.com</field>
            <field name="email_to">{{object.create_uid.email}};sales@viet-toan.com</field>
            <field name="email_cc">david.le@viet-toan.com</field>
            <field name="reply_to">noreply@viet-toan.com</field>
            <field name="auto_delete" eval="True" />
            <field name="lang">{{object.partner_id.lang}}</field>
            <field name="body_html" type="html">
                <table border="0" cellpadding="0" cellspacing="0" style="box-sizing:border-box;padding-top: 16px; background-color: #F1F1F1; font-family:Verdana, Arial,sans-serif; color: #454748; width: 100%; border-collapse:separate;" width="100%"><tbody><tr><td align="center">
                <table border="0" cellpadding="0" cellspacing="0" width="590" style="box-sizing:border-box;padding: 16px; background-color: white; color: #454748; border-collapse:separate;">
                <tbody>
                    <!-- HEADER -->
                    <!--
                    <tr>
                        <td align="center" style="min-width: 590px;">
                            <table border="0" cellpadding="0" cellspacing="0" width="590" style="box-sizing:border-box;min-width: 590px; background-color: white; padding: 0px 8px 0px 8px; border-collapse:separate;">
                                <tbody><tr><td valign="middle">
                                    <span style="font-size: 10px;">Welcome to Odoo</span><br/>
                                    <span style="font-size: 20px; font-weight: bold;">
                                        <t t-out="object.name or ''" data-oe-t-inline="true" contenteditable="false">Marc Demo</t>
                                    </span>
                                </td><td valign="middle" align="right">
                                    <img t-attf-src="/logo.png?company={{ object.company_id.id }}" style="border-style:none;box-sizing:border-box;vertical-align:middle;padding: 0px; margin: 0px; height: 0px; width: 80px;" t-att-alt="object.company_id.name" width="80px" height="0">
                                </td></tr>
                                <tr><td colspan="2" style="text-align:center;">
                                  <hr width="100%" style="border-style:none;border-top-width:medium;border-left-width:medium;border-bottom-width:medium;border-right-width:medium;overflow-y:visible;overflow-x:visible;height:0px;box-sizing:content-box;background-color:#cccccc;border:medium none;clear:both;display:block;font-size:0px;min-height:1px;line-height:0; margin: 16px 0px 16px 0px;">
                                </td></tr>
                            </tbody></table>
                        </td>
                    </tr>
                    -->
                    <!-- CONTENT -->
                    <tr>
                        <td align="center" style="min-width: 590px;">
                            <table border="0" cellpadding="0" cellspacing="0" width="590" style="box-sizing:border-box;min-width: 590px; background-color: white; padding: 0px 8px 0px 8px; border-collapse:separate;">
                                <tbody><tr><td valign="top" style="font-size: 13px;">
                                    <div style="box-sizing:border-box;font-size:13px;" bis_skin_checked="1">
                                        Dear Sales<br/>A new Lead has just been created in the system. Please follow up and take care of this Lead carefully. It is recommended to update the state of the Lead frequently.<br/>
                                        <br/>Hello <strong style="box-sizing:border-box;font-weight:bolder;"><i><t t-out="object.create_uid.name or ''" data-oe-t-inline="true" contenteditable="false">Sales</t></i></strong>
                                        <br/>A new lead has been created in the system:
                                        <br/>- Lead Name: <strong style="box-sizing:border-box;font-weight:bolder;"><i><t t-out="object.name or ''" data-oe-t-inline="true" contenteditable="false">Lead Name</t></i></strong>.
                                        <br/>- Contact: <strong style="box-sizing:border-box;font-weight:bolder;"><i><t t-out="object.contact_name or ''" data-oe-t-inline="true" contenteditable="false">Contact</t></i></strong>.
                                        <br/>- Phone: <strong style="box-sizing:border-box;font-weight:bolder;"><i><t t-out="object.phone or ''" data-oe-t-inline="true" contenteditable="false">Phone</t></i></strong>.
                                        <br/>Please follow up with this lead promptly.
                                        <br/>Best regards,
                                        The CRM Team

                                        <br/><br/>
                                        <div style="box-sizing:border-box;font-size:13px;margin: 16px 0px 16px 0px;" bis_skin_checked="1">
                                            <font color="#ffffff">
                                                <span style="background-color: #875a7b; padding: 8px 16px; text-decoration-thickness: initial; text-decoration-style: initial; text-decoration-color: initial; border-radius: 5px;">
                                                <a t-att-href="'/mail/view?model=crm.lead&amp;res_id=' + str(object.id)" style="box-sizing:border-box;background-color: #875A7B; padding: 8px 16px 8px 16px; text-decoration: none; color: #fff; border-radius: 5px; font-size:13px;">
                                                Xem Lead
                                                </a>
                                                </span>
                                            </font>
                                            <br/>
                                        </div>
                                    </div>
                                </td></tr>
                            </tbody></table>
                        </td>
                    </tr>
                    <!-- FOOTER -->
                    <tr>
                        <td align="center" style="min-width: 590px;">
                            <hr width="100%" style="border-top-color:currentcolor;border-image-width:1;border-image-source:none;border-image-slice:100%;border-image-repeat:stretch;border-image-outset:0;border-left-color:currentcolor;border-bottom-color:currentcolor;border-right-color:currentcolor;border-style:none;border-top-width:medium;border-left-width:medium;border-bottom-width:medium;border-right-width:medium;overflow-y:visible;overflow-x:visible;height:0px;box-sizing:content-box;background-color:#cccccc;border:medium none;clear:both;display:block;font-size:0px;min-height:1px;line-height:0; margin: 16px 0px 4px 0px;"/>
                            <b style="box-sizing:border-box;font-weight:bolder;"><t t-out="object.company_id.name or ''" data-oe-t-inline="true" contenteditable="false">YourCompany</t></b>
                            <div style="box-sizing:border-box;font-size:13px;opacity: 0.7;" bis_skin_checked="1">
                                <t t-out="object.company_id.phone or ''" data-oe-t-inline="true" contenteditable="false">+1 650-123-4567</t>
                                <t t-if="object.company_id.email" data-oe-t-group-active="true" data-oe-t-group="0" data-oe-t-inline="true">
                                    | <a t-att-href="'mailto:%s' % object.company_id.email" style="color:inherit;box-sizing:border-box;background-color:transparent;text-decoration:none;" t-out="object.company_id.email or ''" contenteditable="false">info@yourcompany.com</a>
                                </t>
                                <t t-if="object.company_id.website" data-oe-t-group-active="true" data-oe-t-group="1" data-oe-t-inline="true">
                                    | <a t-att-href="'%s' % object.company_id.website" style="color:inherit;box-sizing:border-box;background-color:transparent;text-decoration:none;" t-out="object.company_id.website or ''" contenteditable="false">http://www.example.com</a>
                                </t>
                            </div>
                        </td>
                    </tr>
                </tbody>
                </table>
                </td></tr>
                <!-- POWERED BY -->
                <tr><td align="center" style="min-width: 590px;">
                    <table border="0" cellpadding="0" cellspacing="0" width="590" style="box-sizing:border-box;min-width: 590px; background-color: #F1F1F1; color: #454748; padding: 8px; border-collapse:separate;">
                      <tbody><tr><td style="text-align: center; font-size: 13px;">
                        Powered by <a target="_blank" href="https://www.odoo.com?utm_source=db&amp;utm_medium=auth" style="text-decoration:none;box-sizing:border-box;background-color:transparent;color: #875A7B;">Odoo</a>
                      </td></tr>
                    </tbody></table>
                </td></tr>
                </tbody>
                </table>
            </field>
        </record>
        <record id="freight_crm_lead_reminder_notification_template_5_days" model="mail.template">
            <field name="name">CRM: 5 ngày trôi qua, bạn đã chăm sóc khách hàng này chưa - QWeb</field>
            <field name="model_id" ref="crm.model_crm_lead" />
            <field name="subject">CRM: 5 days have passed, have you taken care of this Lead yet?</field>
            <field name="email_from">noreply@viet-toan.com</field>
            <field name="email_to">{{object.create_uid.email}};sales@viet-toan.com</field>
            <field name="email_cc">david.le@viet-toan.com</field>
            <field name="reply_to">noreply@viet-toan.com</field>
            <field name="auto_delete" eval="True" />
            <field name="lang">{{object.partner_id.lang}}</field>
            <field name="body_html" type="html">
                <table border="0" cellpadding="0" cellspacing="0" style="box-sizing:border-box;padding-top: 16px; background-color: #F1F1F1; font-family:Verdana, Arial,sans-serif; color: #454748; width: 100%; border-collapse:separate;" width="100%"><tbody><tr><td align="center">
                <table border="0" cellpadding="0" cellspacing="0" width="590" style="box-sizing:border-box;padding: 16px; background-color: white; color: #454748; border-collapse:separate;">
                <tbody>
                    <!-- CONTENT -->
                    <tr>
                        <td align="center" style="min-width: 590px;">
                            <table border="0" cellpadding="0" cellspacing="0" width="590" style="box-sizing:border-box;min-width: 590px; background-color: white; padding: 0px 8px 0px 8px; border-collapse:separate;">
                                <tbody><tr><td valign="top" style="font-size: 13px;">
                                    <div style="box-sizing:border-box;font-size:13px;" bis_skin_checked="1">
                                    <br/>Hello <strong style="box-sizing:border-box;font-weight:bolder;"><i><t t-out="object.create_uid.name or ''" data-oe-t-inline="true" contenteditable="false">Sales</t></i></strong>
                                    <br/>5 days have passed, have you followed up with this Lead yet? Please ignore this message once an action was taken.<br/>
                                    <br/>- Lead Name: <strong style="box-sizing:border-box;font-weight:bolder;"><i><t t-out="object.name or ''" data-oe-t-inline="true" contenteditable="false">Lead Name</t></i></strong>.
                                    <br/>- Contact: <strong style="box-sizing:border-box;font-weight:bolder;"><i><t t-out="object.contact_name or ''" data-oe-t-inline="true" contenteditable="false">Contact</t></i></strong>.
                                    <br/>- Phone: <strong style="box-sizing:border-box;font-weight:bolder;"><i><t t-out="object.phone or ''" data-oe-t-inline="true" contenteditable="false">Phone</t></i></strong>.
                                    <br/>Please follow up with this lead promptly.
                                    <br/>Best regards,
                                    The CRM Team

                                    <br/><br/>
                                        <div style="box-sizing:border-box;font-size:13px;margin: 16px 0px 16px 0px;" bis_skin_checked="1">
                                            <font color="#ffffff"><span style="background-color: #875a7b; padding: 8px 16px; text-decoration-thickness: initial; text-decoration-style: initial; text-decoration-color: initial; border-radius: 5px;">
                                                <a t-att-href="'/mail/view?model=crm.lead&amp;res_id=' + str(object.id)" style="box-sizing:border-box;background-color: #875A7B; padding: 8px 16px 8px 16px; text-decoration: none; color: #fff; border-radius: 5px; font-size:13px;">
                                                Xem Lead
                                                </a>
                                            </span></font>
                                        <br/></div>
                                    </div>
                                </td></tr>
                            </tbody></table>
                        </td>
                    </tr>
                    <!-- FOOTER -->
                    <tr>
                        <td align="center" style="min-width: 590px;">
                            <hr width="100%" style="border-top-color:currentcolor;border-image-width:1;border-image-source:none;border-image-slice:100%;border-image-repeat:stretch;border-image-outset:0;border-left-color:currentcolor;border-bottom-color:currentcolor;border-right-color:currentcolor;border-style:none;border-top-width:medium;border-left-width:medium;border-bottom-width:medium;border-right-width:medium;overflow-y:visible;overflow-x:visible;height:0px;box-sizing:content-box;background-color:#cccccc;border:medium none;clear:both;display:block;font-size:0px;min-height:1px;line-height:0; margin: 16px 0px 4px 0px;"/>
                            <b style="box-sizing:border-box;font-weight:bolder;"><t t-out="object.company_id.name or ''" data-oe-t-inline="true" contenteditable="false">YourCompany</t></b>
                            <div style="box-sizing:border-box;font-size:13px;opacity: 0.7;" bis_skin_checked="1">
                                <t t-out="object.company_id.phone or ''" data-oe-t-inline="true" contenteditable="false">+1 650-123-4567</t>
                                <t t-if="object.company_id.email" data-oe-t-group-active="true" data-oe-t-group="0" data-oe-t-inline="true">
                                    | <a t-att-href="'mailto:%s' % object.company_id.email" style="color:inherit;box-sizing:border-box;background-color:transparent;text-decoration:none;" t-out="object.company_id.email or ''" contenteditable="false">info@yourcompany.com</a>
                                </t>
                                <t t-if="object.company_id.website" data-oe-t-group-active="true" data-oe-t-group="1" data-oe-t-inline="true">
                                    | <a t-att-href="'%s' % object.company_id.website" style="color:inherit;box-sizing:border-box;background-color:transparent;text-decoration:none;" t-out="object.company_id.website or ''" contenteditable="false">http://www.example.com</a>
                                </t>
                            </div>
                        </td>
                    </tr>
                </tbody>
                </table>
                </td></tr>
                <!-- POWERED BY -->
                <tr><td align="center" style="min-width: 590px;">
                    <table border="0" cellpadding="0" cellspacing="0" width="590" style="box-sizing:border-box;min-width: 590px; background-color: #F1F1F1; color: #454748; padding: 8px; border-collapse:separate;">
                      <tbody><tr><td style="text-align: center; font-size: 13px;">
                        Powered by <a target="_blank" href="https://www.odoo.com?utm_source=db&amp;utm_medium=auth" style="text-decoration:none;box-sizing:border-box;background-color:transparent;color: #875A7B;">Odoo</a>
                      </td></tr>
                    </tbody></table>
                </td></tr>
                </tbody></table>
            </field>
        </record>
        <record id="freight_crm_lead_reminder_notification_template_10_days" model="mail.template">
            <field name="name">CRM: 10 ngày trôi qua, bạn đã chăm sóc khách hàng này chưa - QWeb</field>
            <field name="model_id" ref="crm.model_crm_lead" />
            <field name="subject">CRM: 10 days have passed, have you taken care of this Lead yet?</field>
            <field name="email_from">noreply@viet-toan.com</field>
            <field name="email_to">{{object.create_uid.email}};sales@viet-toan.com</field>
            <field name="email_cc">david.le@viet-toan.com</field>
            <field name="reply_to">noreply@viet-toan.com</field>
            <field name="auto_delete" eval="True" />
            <field name="lang">{{object.partner_id.lang}}</field>
            <field name="body_html" type="html">
                <table border="0" cellpadding="0" cellspacing="0" style="box-sizing:border-box;padding-top: 16px; background-color: #F1F1F1; font-family:Verdana, Arial,sans-serif; color: #454748; width: 100%; border-collapse:separate;" width="100%"><tbody><tr><td align="center">
                <table border="0" cellpadding="0" cellspacing="0" width="590" style="box-sizing:border-box;padding: 16px; background-color: white; color: #454748; border-collapse:separate;">
                <tbody>
                    <!-- CONTENT -->
                    <tr>
                        <td align="center" style="min-width: 590px;">
                            <table border="0" cellpadding="0" cellspacing="0" width="590" style="box-sizing:border-box;min-width: 590px; background-color: white; padding: 0px 8px 0px 8px; border-collapse:separate;">
                                <tbody><tr><td valign="top" style="font-size: 13px;">
                                    <div style="box-sizing:border-box;font-size:13px;" bis_skin_checked="1">
                                    <br/>Hello <strong style="box-sizing:border-box;font-weight:bolder;"><i><t t-out="object.create_uid.name or ''" data-oe-t-inline="true" contenteditable="false">Sales</t></i></strong>
                                    <br/>10 days have passed, have you followed up with this Lead yet? Please ignore this message once an action was taken.<br/>
                                    <br/>- Lead Name: <strong style="box-sizing:border-box;font-weight:bolder;"><i><t t-out="object.name or ''" data-oe-t-inline="true" contenteditable="false">Lead Name</t></i></strong>.
                                    <br/>- Contact: <strong style="box-sizing:border-box;font-weight:bolder;"><i><t t-out="object.contact_name or ''" data-oe-t-inline="true" contenteditable="false">Contact</t></i></strong>.
                                    <br/>- Phone: <strong style="box-sizing:border-box;font-weight:bolder;"><i><t t-out="object.phone or ''" data-oe-t-inline="true" contenteditable="false">Phone</t></i></strong>.
                                    <br/>Please follow up with this lead promptly.
                                    <br/>Best regards,
                                    The CRM Team

                                    <br/><br/>
                                        <div style="box-sizing:border-box;font-size:13px;margin: 16px 0px 16px 0px;" bis_skin_checked="1">
                                            <font color="#ffffff"><span style="background-color: #875a7b; padding: 8px 16px; text-decoration-thickness: initial; text-decoration-style: initial; text-decoration-color: initial; border-radius: 5px;">
                                                <a t-att-href="'/mail/view?model=crm.lead&amp;res_id=' + str(object.id)" style="box-sizing:border-box;background-color: #875A7B; padding: 8px 16px 8px 16px; text-decoration: none; color: #fff; border-radius: 5px; font-size:13px;">
                                                Xem Lead
                                                </a>
                                            </span></font>
                                        <br/></div>
                                    </div>
                                </td></tr>
                            </tbody></table>
                        </td>
                    </tr>
                    <!-- FOOTER -->
                    <tr>
                        <td align="center" style="min-width: 590px;">
                            <hr width="100%" style="border-top-color:currentcolor;border-image-width:1;border-image-source:none;border-image-slice:100%;border-image-repeat:stretch;border-image-outset:0;border-left-color:currentcolor;border-bottom-color:currentcolor;border-right-color:currentcolor;border-style:none;border-top-width:medium;border-left-width:medium;border-bottom-width:medium;border-right-width:medium;overflow-y:visible;overflow-x:visible;height:0px;box-sizing:content-box;background-color:#cccccc;border:medium none;clear:both;display:block;font-size:0px;min-height:1px;line-height:0; margin: 16px 0px 4px 0px;"/>
                            <b style="box-sizing:border-box;font-weight:bolder;"><t t-out="object.company_id.name or ''" data-oe-t-inline="true" contenteditable="false">YourCompany</t></b>
                            <div style="box-sizing:border-box;font-size:13px;opacity: 0.7;" bis_skin_checked="1">
                                <t t-out="object.company_id.phone or ''" data-oe-t-inline="true" contenteditable="false">+1 650-123-4567</t>
                                <t t-if="object.company_id.email" data-oe-t-group-active="true" data-oe-t-group="0" data-oe-t-inline="true">
                                    | <a t-att-href="'mailto:%s' % object.company_id.email" style="color:inherit;box-sizing:border-box;background-color:transparent;text-decoration:none;" t-out="object.company_id.email or ''" contenteditable="false">info@yourcompany.com</a>
                                </t>
                                <t t-if="object.company_id.website" data-oe-t-group-active="true" data-oe-t-group="1" data-oe-t-inline="true">
                                    | <a t-att-href="'%s' % object.company_id.website" style="color:inherit;box-sizing:border-box;background-color:transparent;text-decoration:none;" t-out="object.company_id.website or ''" contenteditable="false">http://www.example.com</a>
                                </t>
                            </div>
                        </td>
                    </tr>
                </tbody>
                </table>
                </td></tr>
                <!-- POWERED BY -->
                <tr><td align="center" style="min-width: 590px;">
                    <table border="0" cellpadding="0" cellspacing="0" width="590" style="box-sizing:border-box;min-width: 590px; background-color: #F1F1F1; color: #454748; padding: 8px; border-collapse:separate;">
                      <tbody><tr><td style="text-align: center; font-size: 13px;">
                        Powered by <a target="_blank" href="https://www.odoo.com?utm_source=db&amp;utm_medium=auth" style="text-decoration:none;box-sizing:border-box;background-color:transparent;color: #875A7B;">Odoo</a>
                      </td></tr>
                    </tbody></table>
                </td></tr>
                </tbody></table>
            </field>
        </record>
        <record id="freight_crm_lead_reminder_notification_template_20_days" model="mail.template">
            <field name="name">CRM: 20 ngày trôi qua, bạn đã chăm sóc khách hàng này chưa - QWeb</field>
            <field name="model_id" ref="crm.model_crm_lead" />
            <field name="subject">CRM: 20 days have passed, have you taken care of this Lead yet?</field>
            <field name="email_from">noreply@viet-toan.com</field>
            <field name="email_to">{{object.create_uid.email}};sales@viet-toan.com</field>
            <field name="email_cc">david.le@viet-toan.com</field>
            <field name="reply_to">noreply@viet-toan.com</field>
            <field name="auto_delete" eval="True" />
            <field name="lang">{{object.partner_id.lang}}</field>
            <field name="body_html" type="html">
                <table border="0" cellpadding="0" cellspacing="0" style="box-sizing:border-box;padding-top: 16px; background-color: #F1F1F1; font-family:Verdana, Arial,sans-serif; color: #454748; width: 100%; border-collapse:separate;" width="100%"><tbody><tr><td align="center">
                <table border="0" cellpadding="0" cellspacing="0" width="590" style="box-sizing:border-box;padding: 16px; background-color: white; color: #454748; border-collapse:separate;">
                <tbody>
                    <!-- CONTENT -->
                    <tr>
                        <td align="center" style="min-width: 590px;">
                            <table border="0" cellpadding="0" cellspacing="0" width="590" style="box-sizing:border-box;min-width: 590px; background-color: white; padding: 0px 8px 0px 8px; border-collapse:separate;">
                                <tbody><tr><td valign="top" style="font-size: 13px;">
                                    <div style="box-sizing:border-box;font-size:13px;" bis_skin_checked="1">
                                    <br/>Hello <strong style="box-sizing:border-box;font-weight:bolder;"><i><t t-out="object.create_uid.name or ''" data-oe-t-inline="true" contenteditable="false">Sales</t></i></strong>
                                    <br/>20 days have passed, have you followed up with this Lead yet? Please ignore this message once an action was taken.<br/>
                                    <br/>- Lead Name: <strong style="box-sizing:border-box;font-weight:bolder;"><i><t t-out="object.name or ''" data-oe-t-inline="true" contenteditable="false">Lead Name</t></i></strong>.
                                    <br/>- Contact: <strong style="box-sizing:border-box;font-weight:bolder;"><i><t t-out="object.contact_name or ''" data-oe-t-inline="true" contenteditable="false">Contact</t></i></strong>.
                                    <br/>- Phone: <strong style="box-sizing:border-box;font-weight:bolder;"><i><t t-out="object.phone or ''" data-oe-t-inline="true" contenteditable="false">Phone</t></i></strong>.
                                    <br/>Please follow up with this lead promptly.
                                    <br/>Best regards,
                                    The CRM Team

                                    <br/><br/>
                                        <div style="box-sizing:border-box;font-size:13px;margin: 16px 0px 16px 0px;" bis_skin_checked="1">
                                            <font color="#ffffff"><span style="background-color: #875a7b; padding: 8px 16px; text-decoration-thickness: initial; text-decoration-style: initial; text-decoration-color: initial; border-radius: 5px;">
                                                <a t-att-href="'/mail/view?model=crm.lead&amp;res_id=' + str(object.id)" style="box-sizing:border-box;background-color: #875A7B; padding: 8px 16px 8px 16px; text-decoration: none; color: #fff; border-radius: 5px; font-size:13px;">
                                                Xem Lead
                                                </a>
                                            </span></font>
                                        <br/></div>
                                    </div>
                                </td></tr>
                            </tbody></table>
                        </td>
                    </tr>
                    <!-- FOOTER -->
                    <tr>
                        <td align="center" style="min-width: 590px;">
                            <hr width="100%" style="border-top-color:currentcolor;border-image-width:1;border-image-source:none;border-image-slice:100%;border-image-repeat:stretch;border-image-outset:0;border-left-color:currentcolor;border-bottom-color:currentcolor;border-right-color:currentcolor;border-style:none;border-top-width:medium;border-left-width:medium;border-bottom-width:medium;border-right-width:medium;overflow-y:visible;overflow-x:visible;height:0px;box-sizing:content-box;background-color:#cccccc;border:medium none;clear:both;display:block;font-size:0px;min-height:1px;line-height:0; margin: 16px 0px 4px 0px;"/>
                            <b style="box-sizing:border-box;font-weight:bolder;"><t t-out="object.company_id.name or ''" data-oe-t-inline="true" contenteditable="false">YourCompany</t></b>
                            <div style="box-sizing:border-box;font-size:13px;opacity: 0.7;" bis_skin_checked="1">
                                <t t-out="object.company_id.phone or ''" data-oe-t-inline="true" contenteditable="false">+1 650-123-4567</t>
                                <t t-if="object.company_id.email" data-oe-t-group-active="true" data-oe-t-group="0" data-oe-t-inline="true">
                                    | <a t-att-href="'mailto:%s' % object.company_id.email" style="color:inherit;box-sizing:border-box;background-color:transparent;text-decoration:none;" t-out="object.company_id.email or ''" contenteditable="false">info@yourcompany.com</a>
                                </t>
                                <t t-if="object.company_id.website" data-oe-t-group-active="true" data-oe-t-group="1" data-oe-t-inline="true">
                                    | <a t-att-href="'%s' % object.company_id.website" style="color:inherit;box-sizing:border-box;background-color:transparent;text-decoration:none;" t-out="object.company_id.website or ''" contenteditable="false">http://www.example.com</a>
                                </t>
                            </div>
                        </td>
                    </tr>
                </tbody>
                </table>
                </td></tr>
                <!-- POWERED BY -->
                <tr><td align="center" style="min-width: 590px;">
                    <table border="0" cellpadding="0" cellspacing="0" width="590" style="box-sizing:border-box;min-width: 590px; background-color: #F1F1F1; color: #454748; padding: 8px; border-collapse:separate;">
                      <tbody><tr><td style="text-align: center; font-size: 13px;">
                        Powered by <a target="_blank" href="https://www.odoo.com?utm_source=db&amp;utm_medium=auth" style="text-decoration:none;box-sizing:border-box;background-color:transparent;color: #875A7B;">Odoo</a>
                      </td></tr>
                    </tbody></table>
                </td></tr>
                </tbody></table>
            </field>
        </record>
        <record id="freight_crm_lead_reminder_notification_template_30_days" model="mail.template">
            <field name="name">CRM: 30 ngày trôi qua, bạn đã chăm sóc khách hàng này chưa - QWeb</field>
            <field name="model_id" ref="crm.model_crm_lead" />
            <field name="subject">CRM: 30 days have passed, have you taken care of this Lead yet?</field>
            <field name="email_from">noreply@viet-toan.com</field>
            <field name="email_to">{{object.create_uid.email}};sales@viet-toan.com</field>
            <field name="email_cc">david.le@viet-toan.com</field>
            <field name="reply_to">noreply@viet-toan.com</field>
            <field name="auto_delete" eval="True" />
            <field name="lang">{{object.partner_id.lang}}</field>
            <field name="body_html" type="html">
                <table border="0" cellpadding="0" cellspacing="0" style="box-sizing:border-box;padding-top: 16px; background-color: #F1F1F1; font-family:Verdana, Arial,sans-serif; color: #454748; width: 100%; border-collapse:separate;" width="100%"><tbody><tr><td align="center">
                <table border="0" cellpadding="0" cellspacing="0" width="590" style="box-sizing:border-box;padding: 16px; background-color: white; color: #454748; border-collapse:separate;">
                <tbody>
                    <!-- CONTENT -->
                    <tr>
                        <td align="center" style="min-width: 590px;">
                            <table border="0" cellpadding="0" cellspacing="0" width="590" style="box-sizing:border-box;min-width: 590px; background-color: white; padding: 0px 8px 0px 8px; border-collapse:separate;">
                                <tbody><tr><td valign="top" style="font-size: 13px;">
                                    <div style="box-sizing:border-box;font-size:13px;" bis_skin_checked="1">
                                    <br/>Hello <strong style="box-sizing:border-box;font-weight:bolder;"><i><t t-out="object.create_uid.name or ''" data-oe-t-inline="true" contenteditable="false">Sales</t></i></strong>
                                    <br/>30 days have passed, have you followed up with this Lead yet? Please ignore this message once an action was taken.<br/>
                                    <br/>- Lead Name: <strong style="box-sizing:border-box;font-weight:bolder;"><i><t t-out="object.name or ''" data-oe-t-inline="true" contenteditable="false">Lead Name</t></i></strong>.
                                    <br/>- Contact: <strong style="box-sizing:border-box;font-weight:bolder;"><i><t t-out="object.contact_name or ''" data-oe-t-inline="true" contenteditable="false">Contact</t></i></strong>.
                                    <br/>- Phone: <strong style="box-sizing:border-box;font-weight:bolder;"><i><t t-out="object.phone or ''" data-oe-t-inline="true" contenteditable="false">Phone</t></i></strong>.
                                    <br/>Please follow up with this lead promptly.
                                    <br/>Best regards,
                                    The CRM Team

                                    <br/><br/>
                                        <div style="box-sizing:border-box;font-size:13px;margin: 16px 0px 16px 0px;" bis_skin_checked="1">
                                            <font color="#ffffff"><span style="background-color: #875a7b; padding: 8px 16px; text-decoration-thickness: initial; text-decoration-style: initial; text-decoration-color: initial; border-radius: 5px;">
                                                <a t-att-href="'/mail/view?model=crm.lead&amp;res_id=' + str(object.id)" style="box-sizing:border-box;background-color: #875A7B; padding: 8px 16px 8px 16px; text-decoration: none; color: #fff; border-radius: 5px; font-size:13px;">
                                                Xem Lead
                                                </a>
                                            </span></font>
                                        <br/></div>
                                    </div>
                                </td></tr>
                            </tbody></table>
                        </td>
                    </tr>
                    <!-- FOOTER -->
                    <tr>
                        <td align="center" style="min-width: 590px;">
                            <hr width="100%" style="border-top-color:currentcolor;border-image-width:1;border-image-source:none;border-image-slice:100%;border-image-repeat:stretch;border-image-outset:0;border-left-color:currentcolor;border-bottom-color:currentcolor;border-right-color:currentcolor;border-style:none;border-top-width:medium;border-left-width:medium;border-bottom-width:medium;border-right-width:medium;overflow-y:visible;overflow-x:visible;height:0px;box-sizing:content-box;background-color:#cccccc;border:medium none;clear:both;display:block;font-size:0px;min-height:1px;line-height:0; margin: 16px 0px 4px 0px;"/>
                            <b style="box-sizing:border-box;font-weight:bolder;"><t t-out="object.company_id.name or ''" data-oe-t-inline="true" contenteditable="false">YourCompany</t></b>
                            <div style="box-sizing:border-box;font-size:13px;opacity: 0.7;" bis_skin_checked="1">
                                <t t-out="object.company_id.phone or ''" data-oe-t-inline="true" contenteditable="false">+1 650-123-4567</t>
                                <t t-if="object.company_id.email" data-oe-t-group-active="true" data-oe-t-group="0" data-oe-t-inline="true">
                                    | <a t-att-href="'mailto:%s' % object.company_id.email" style="color:inherit;box-sizing:border-box;background-color:transparent;text-decoration:none;" t-out="object.company_id.email or ''" contenteditable="false">info@yourcompany.com</a>
                                </t>
                                <t t-if="object.company_id.website" data-oe-t-group-active="true" data-oe-t-group="1" data-oe-t-inline="true">
                                    | <a t-att-href="'%s' % object.company_id.website" style="color:inherit;box-sizing:border-box;background-color:transparent;text-decoration:none;" t-out="object.company_id.website or ''" contenteditable="false">http://www.example.com</a>
                                </t>
                            </div>
                        </td>
                    </tr>
                </tbody>
                </table>
                </td></tr>
                <!-- POWERED BY -->
                <tr><td align="center" style="min-width: 590px;">
                    <table border="0" cellpadding="0" cellspacing="0" width="590" style="box-sizing:border-box;min-width: 590px; background-color: #F1F1F1; color: #454748; padding: 8px; border-collapse:separate;">
                      <tbody><tr><td style="text-align: center; font-size: 13px;">
                        Powered by <a target="_blank" href="https://www.odoo.com?utm_source=db&amp;utm_medium=auth" style="text-decoration:none;box-sizing:border-box;background-color:transparent;color: #875A7B;">Odoo</a>
                      </td></tr>
                    </tbody></table>
                </td></tr>
                </tbody></table>
            </field>
        </record>
        <record id="freight_crm_lead_reminder_notification_template_40_days" model="mail.template">
            <field name="name">CRM: 40 ngày trôi qua, bạn đã chăm sóc khách hàng này chưa - QWeb</field>
            <field name="model_id" ref="crm.model_crm_lead" />
            <field name="subject">CRM: 40 days have passed, have you taken care of this Lead yet?</field>
            <field name="email_from">noreply@viet-toan.com</field>
            <field name="email_to">{{object.create_uid.email}};sales@viet-toan.com</field>
            <field name="email_cc">david.le@viet-toan.com</field>
            <field name="reply_to">noreply@viet-toan.com</field>
            <field name="auto_delete" eval="True" />
            <field name="lang">{{object.partner_id.lang}}</field>
            <field name="body_html" type="html">
                <table border="0" cellpadding="0" cellspacing="0" style="box-sizing:border-box;padding-top: 16px; background-color: #F1F1F1; font-family:Verdana, Arial,sans-serif; color: #454748; width: 100%; border-collapse:separate;" width="100%"><tbody><tr><td align="center">
                <table border="0" cellpadding="0" cellspacing="0" width="590" style="box-sizing:border-box;padding: 16px; background-color: white; color: #454748; border-collapse:separate;">
                <tbody>
                    <!-- CONTENT -->
                    <tr>
                        <td align="center" style="min-width: 590px;">
                            <table border="0" cellpadding="0" cellspacing="0" width="590" style="box-sizing:border-box;min-width: 590px; background-color: white; padding: 0px 8px 0px 8px; border-collapse:separate;">
                                <tbody><tr><td valign="top" style="font-size: 13px;">
                                    <div style="box-sizing:border-box;font-size:13px;" bis_skin_checked="1">
                                    <br/>Hello <strong style="box-sizing:border-box;font-weight:bolder;"><i><t t-out="object.create_uid.name or ''" data-oe-t-inline="true" contenteditable="false">Sales</t></i></strong>
                                    <br/>40 days have passed, have you followed up with this Lead yet? Please ignore this message once an action was taken.<br/>
                                    <br/>- Lead Name: <strong style="box-sizing:border-box;font-weight:bolder;"><i><t t-out="object.name or ''" data-oe-t-inline="true" contenteditable="false">Lead Name</t></i></strong>.
                                    <br/>- Contact: <strong style="box-sizing:border-box;font-weight:bolder;"><i><t t-out="object.contact_name or ''" data-oe-t-inline="true" contenteditable="false">Contact</t></i></strong>.
                                    <br/>- Phone: <strong style="box-sizing:border-box;font-weight:bolder;"><i><t t-out="object.phone or ''" data-oe-t-inline="true" contenteditable="false">Phone</t></i></strong>.
                                    <br/>Please follow up with this lead promptly.
                                    <br/>Best regards,
                                    The CRM Team

                                    <br/><br/>
                                        <div style="box-sizing:border-box;font-size:13px;margin: 16px 0px 16px 0px;" bis_skin_checked="1">
                                            <font color="#ffffff"><span style="background-color: #875a7b; padding: 8px 16px; text-decoration-thickness: initial; text-decoration-style: initial; text-decoration-color: initial; border-radius: 5px;">
                                                <a t-att-href="'/mail/view?model=crm.lead&amp;res_id=' + str(object.id)" style="box-sizing:border-box;background-color: #875A7B; padding: 8px 16px 8px 16px; text-decoration: none; color: #fff; border-radius: 5px; font-size:13px;">
                                                Xem Lead
                                                </a>
                                            </span></font>
                                        <br/></div>
                                    </div>
                                </td></tr>
                            </tbody></table>
                        </td>
                    </tr>
                    <!-- FOOTER -->
                    <tr>
                        <td align="center" style="min-width: 590px;">
                            <hr width="100%" style="border-top-color:currentcolor;border-image-width:1;border-image-source:none;border-image-slice:100%;border-image-repeat:stretch;border-image-outset:0;border-left-color:currentcolor;border-bottom-color:currentcolor;border-right-color:currentcolor;border-style:none;border-top-width:medium;border-left-width:medium;border-bottom-width:medium;border-right-width:medium;overflow-y:visible;overflow-x:visible;height:0px;box-sizing:content-box;background-color:#cccccc;border:medium none;clear:both;display:block;font-size:0px;min-height:1px;line-height:0; margin: 16px 0px 4px 0px;"/>
                            <b style="box-sizing:border-box;font-weight:bolder;"><t t-out="object.company_id.name or ''" data-oe-t-inline="true" contenteditable="false">YourCompany</t></b>
                            <div style="box-sizing:border-box;font-size:13px;opacity: 0.7;" bis_skin_checked="1">
                                <t t-out="object.company_id.phone or ''" data-oe-t-inline="true" contenteditable="false">+1 650-123-4567</t>
                                <t t-if="object.company_id.email" data-oe-t-group-active="true" data-oe-t-group="0" data-oe-t-inline="true">
                                    | <a t-att-href="'mailto:%s' % object.company_id.email" style="color:inherit;box-sizing:border-box;background-color:transparent;text-decoration:none;" t-out="object.company_id.email or ''" contenteditable="false">info@yourcompany.com</a>
                                </t>
                                <t t-if="object.company_id.website" data-oe-t-group-active="true" data-oe-t-group="1" data-oe-t-inline="true">
                                    | <a t-att-href="'%s' % object.company_id.website" style="color:inherit;box-sizing:border-box;background-color:transparent;text-decoration:none;" t-out="object.company_id.website or ''" contenteditable="false">http://www.example.com</a>
                                </t>
                            </div>
                        </td>
                    </tr>
                </tbody>
                </table>
                </td></tr>
                <!-- POWERED BY -->
                <tr><td align="center" style="min-width: 590px;">
                    <table border="0" cellpadding="0" cellspacing="0" width="590" style="box-sizing:border-box;min-width: 590px; background-color: #F1F1F1; color: #454748; padding: 8px; border-collapse:separate;">
                      <tbody><tr><td style="text-align: center; font-size: 13px;">
                        Powered by <a target="_blank" href="https://www.odoo.com?utm_source=db&amp;utm_medium=auth" style="text-decoration:none;box-sizing:border-box;background-color:transparent;color: #875A7B;">Odoo</a>
                      </td></tr>
                    </tbody></table>
                </td></tr>
                </tbody></table>
            </field>
        </record>
        <record id="freight_crm_lead_reminder_notification_template_50_days" model="mail.template">
            <field name="name">CRM: 50 ngày trôi qua, bạn đã chăm sóc khách hàng này chưa - QWeb</field>
            <field name="model_id" ref="crm.model_crm_lead" />
            <field name="subject">CRM: 50 days have passed, have you taken care of this Lead yet?</field>
            <field name="email_from">noreply@viet-toan.com</field>
            <field name="email_to">{{object.create_uid.email}};sales@viet-toan.com</field>
            <field name="email_cc">david.le@viet-toan.com</field>
            <field name="reply_to">noreply@viet-toan.com</field>
            <field name="auto_delete" eval="True" />
            <field name="lang">{{object.partner_id.lang}}</field>
            <field name="body_html" type="html">
                <table border="0" cellpadding="0" cellspacing="0" style="box-sizing:border-box;padding-top: 16px; background-color: #F1F1F1; font-family:Verdana, Arial,sans-serif; color: #454748; width: 100%; border-collapse:separate;" width="100%"><tbody><tr><td align="center">
                <table border="0" cellpadding="0" cellspacing="0" width="590" style="box-sizing:border-box;padding: 16px; background-color: white; color: #454748; border-collapse:separate;">
                <tbody>
                    <!-- CONTENT -->
                    <tr>
                        <td align="center" style="min-width: 590px;">
                            <table border="0" cellpadding="0" cellspacing="0" width="590" style="box-sizing:border-box;min-width: 590px; background-color: white; padding: 0px 8px 0px 8px; border-collapse:separate;">
                                <tbody><tr><td valign="top" style="font-size: 13px;">
                                    <div style="box-sizing:border-box;font-size:13px;" bis_skin_checked="1">
                                    <br/>Hello <strong style="box-sizing:border-box;font-weight:bolder;"><i><t t-out="object.create_uid.name or ''" data-oe-t-inline="true" contenteditable="false">Sales</t></i></strong>
                                    <br/>50 days have passed, have you followed up with this Lead yet? Please ignore this message once an action was taken.<br/>
                                    <br/>- Lead Name: <strong style="box-sizing:border-box;font-weight:bolder;"><i><t t-out="object.name or ''" data-oe-t-inline="true" contenteditable="false">Lead Name</t></i></strong>.
                                    <br/>- Contact: <strong style="box-sizing:border-box;font-weight:bolder;"><i><t t-out="object.contact_name or ''" data-oe-t-inline="true" contenteditable="false">Contact</t></i></strong>.
                                    <br/>- Phone: <strong style="box-sizing:border-box;font-weight:bolder;"><i><t t-out="object.phone or ''" data-oe-t-inline="true" contenteditable="false">Phone</t></i></strong>.
                                    <br/>Please follow up with this lead promptly.
                                    <br/>Best regards,
                                    The CRM Team

                                    <br/><br/>
                                        <div style="box-sizing:border-box;font-size:13px;margin: 16px 0px 16px 0px;" bis_skin_checked="1">
                                            <font color="#ffffff"><span style="background-color: #875a7b; padding: 8px 16px; text-decoration-thickness: initial; text-decoration-style: initial; text-decoration-color: initial; border-radius: 5px;">
                                                <a t-att-href="'/mail/view?model=crm.lead&amp;res_id=' + str(object.id)" style="box-sizing:border-box;background-color: #875A7B; padding: 8px 16px 8px 16px; text-decoration: none; color: #fff; border-radius: 5px; font-size:13px;">
                                                Xem Lead
                                                </a>
                                            </span></font>
                                        <br/></div>
                                    </div>
                                </td></tr>
                            </tbody></table>
                        </td>
                    </tr>
                    <!-- FOOTER -->
                    <tr>
                        <td align="center" style="min-width: 590px;">
                            <hr width="100%" style="border-top-color:currentcolor;border-image-width:1;border-image-source:none;border-image-slice:100%;border-image-repeat:stretch;border-image-outset:0;border-left-color:currentcolor;border-bottom-color:currentcolor;border-right-color:currentcolor;border-style:none;border-top-width:medium;border-left-width:medium;border-bottom-width:medium;border-right-width:medium;overflow-y:visible;overflow-x:visible;height:0px;box-sizing:content-box;background-color:#cccccc;border:medium none;clear:both;display:block;font-size:0px;min-height:1px;line-height:0; margin: 16px 0px 4px 0px;"/>
                            <b style="box-sizing:border-box;font-weight:bolder;"><t t-out="object.company_id.name or ''" data-oe-t-inline="true" contenteditable="false">YourCompany</t></b>
                            <div style="box-sizing:border-box;font-size:13px;opacity: 0.7;" bis_skin_checked="1">
                                <t t-out="object.company_id.phone or ''" data-oe-t-inline="true" contenteditable="false">+1 650-123-4567</t>
                                <t t-if="object.company_id.email" data-oe-t-group-active="true" data-oe-t-group="0" data-oe-t-inline="true">
                                    | <a t-att-href="'mailto:%s' % object.company_id.email" style="color:inherit;box-sizing:border-box;background-color:transparent;text-decoration:none;" t-out="object.company_id.email or ''" contenteditable="false">info@yourcompany.com</a>
                                </t>
                                <t t-if="object.company_id.website" data-oe-t-group-active="true" data-oe-t-group="1" data-oe-t-inline="true">
                                    | <a t-att-href="'%s' % object.company_id.website" style="color:inherit;box-sizing:border-box;background-color:transparent;text-decoration:none;" t-out="object.company_id.website or ''" contenteditable="false">http://www.example.com</a>
                                </t>
                            </div>
                        </td>
                    </tr>
                </tbody>
                </table>
                </td></tr>
                <!-- POWERED BY -->
                <tr><td align="center" style="min-width: 590px;">
                    <table border="0" cellpadding="0" cellspacing="0" width="590" style="box-sizing:border-box;min-width: 590px; background-color: #F1F1F1; color: #454748; padding: 8px; border-collapse:separate;">
                      <tbody><tr><td style="text-align: center; font-size: 13px;">
                        Powered by <a target="_blank" href="https://www.odoo.com?utm_source=db&amp;utm_medium=auth" style="text-decoration:none;box-sizing:border-box;background-color:transparent;color: #875A7B;">Odoo</a>
                      </td></tr>
                    </tbody></table>
                </td></tr>
                </tbody></table>
            </field>
        </record>
        <record id="freight_crm_lead_reminder_notification_template_60_days" model="mail.template">
            <field name="name">CRM: 60 ngày trôi qua, bạn đã chăm sóc khách hàng này chưa - QWeb</field>
            <field name="model_id" ref="crm.model_crm_lead" />
            <field name="subject">CRM: 60 days have passed, have you taken care of this Lead yet?</field>
            <field name="email_from">noreply@viet-toan.com</field>
            <field name="email_to">{{object.create_uid.email}};sales@viet-toan.com</field>
            <field name="email_cc">david.le@viet-toan.com</field>
            <field name="reply_to">noreply@viet-toan.com</field>
            <field name="auto_delete" eval="True" />
            <field name="lang">{{object.partner_id.lang}}</field>
            <field name="body_html" type="html">
                <table border="0" cellpadding="0" cellspacing="0" style="box-sizing:border-box;padding-top: 16px; background-color: #F1F1F1; font-family:Verdana, Arial,sans-serif; color: #454748; width: 100%; border-collapse:separate;" width="100%"><tbody><tr><td align="center">
                <table border="0" cellpadding="0" cellspacing="0" width="590" style="box-sizing:border-box;padding: 16px; background-color: white; color: #454748; border-collapse:separate;">
                <tbody>
                    <!-- CONTENT -->
                    <tr>
                        <td align="center" style="min-width: 590px;">
                            <table border="0" cellpadding="0" cellspacing="0" width="590" style="box-sizing:border-box;min-width: 590px; background-color: white; padding: 0px 8px 0px 8px; border-collapse:separate;">
                                <tbody><tr><td valign="top" style="font-size: 13px;">
                                    <div style="box-sizing:border-box;font-size:13px;" bis_skin_checked="1">
                                    <br/>Hello <strong style="box-sizing:border-box;font-weight:bolder;"><i><t t-out="object.create_uid.name or ''" data-oe-t-inline="true" contenteditable="false">Sales</t></i></strong>
                                    <br/>60 days have passed, have you followed up with this Lead yet? Please ignore this message once an action was taken.<br/>
                                    <br/>- Lead Name: <strong style="box-sizing:border-box;font-weight:bolder;"><i><t t-out="object.name or ''" data-oe-t-inline="true" contenteditable="false">Lead Name</t></i></strong>.
                                    <br/>- Contact: <strong style="box-sizing:border-box;font-weight:bolder;"><i><t t-out="object.contact_name or ''" data-oe-t-inline="true" contenteditable="false">Contact</t></i></strong>.
                                    <br/>- Phone: <strong style="box-sizing:border-box;font-weight:bolder;"><i><t t-out="object.phone or ''" data-oe-t-inline="true" contenteditable="false">Phone</t></i></strong>.
                                    <br/>Please follow up with this lead promptly.
                                    <br/>Best regards,
                                    The CRM Team

                                    <br/><br/>
                                        <div style="box-sizing:border-box;font-size:13px;margin: 16px 0px 16px 0px;" bis_skin_checked="1">
                                            <font color="#ffffff"><span style="background-color: #875a7b; padding: 8px 16px; text-decoration-thickness: initial; text-decoration-style: initial; text-decoration-color: initial; border-radius: 5px;">
                                                <a t-att-href="'/mail/view?model=crm.lead&amp;res_id=' + str(object.id)" style="box-sizing:border-box;background-color: #875A7B; padding: 8px 16px 8px 16px; text-decoration: none; color: #fff; border-radius: 5px; font-size:13px;">
                                                Xem Lead
                                                </a>
                                            </span></font>
                                        <br/></div>
                                    </div>
                                </td></tr>
                            </tbody></table>
                        </td>
                    </tr>
                    <!-- FOOTER -->
                    <tr>
                        <td align="center" style="min-width: 590px;">
                            <hr width="100%" style="border-top-color:currentcolor;border-image-width:1;border-image-source:none;border-image-slice:100%;border-image-repeat:stretch;border-image-outset:0;border-left-color:currentcolor;border-bottom-color:currentcolor;border-right-color:currentcolor;border-style:none;border-top-width:medium;border-left-width:medium;border-bottom-width:medium;border-right-width:medium;overflow-y:visible;overflow-x:visible;height:0px;box-sizing:content-box;background-color:#cccccc;border:medium none;clear:both;display:block;font-size:0px;min-height:1px;line-height:0; margin: 16px 0px 4px 0px;"/>
                            <b style="box-sizing:border-box;font-weight:bolder;"><t t-out="object.company_id.name or ''" data-oe-t-inline="true" contenteditable="false">YourCompany</t></b>
                            <div style="box-sizing:border-box;font-size:13px;opacity: 0.7;" bis_skin_checked="1">
                                <t t-out="object.company_id.phone or ''" data-oe-t-inline="true" contenteditable="false">+1 650-123-4567</t>
                                <t t-if="object.company_id.email" data-oe-t-group-active="true" data-oe-t-group="0" data-oe-t-inline="true">
                                    | <a t-att-href="'mailto:%s' % object.company_id.email" style="color:inherit;box-sizing:border-box;background-color:transparent;text-decoration:none;" t-out="object.company_id.email or ''" contenteditable="false">info@yourcompany.com</a>
                                </t>
                                <t t-if="object.company_id.website" data-oe-t-group-active="true" data-oe-t-group="1" data-oe-t-inline="true">
                                    | <a t-att-href="'%s' % object.company_id.website" style="color:inherit;box-sizing:border-box;background-color:transparent;text-decoration:none;" t-out="object.company_id.website or ''" contenteditable="false">http://www.example.com</a>
                                </t>
                            </div>
                        </td>
                    </tr>
                </tbody>
                </table>
                </td></tr>
                <!-- POWERED BY -->
                <tr><td align="center" style="min-width: 590px;">
                    <table border="0" cellpadding="0" cellspacing="0" width="590" style="box-sizing:border-box;min-width: 590px; background-color: #F1F1F1; color: #454748; padding: 8px; border-collapse:separate;">
                      <tbody><tr><td style="text-align: center; font-size: 13px;">
                        Powered by <a target="_blank" href="https://www.odoo.com?utm_source=db&amp;utm_medium=auth" style="text-decoration:none;box-sizing:border-box;background-color:transparent;color: #875A7B;">Odoo</a>
                      </td></tr>
                    </tbody></table>
                </td></tr>
                </tbody></table>
            </field>
        </record>
    </data>
</odoo>